src/__init__.py
src/main.py
src/models.py
src/todo_manager.py
src/ui_helpers.py
evolved_todo-1.5.0.dist-info/METADATA
evolved_todo-1.5.0.dist-info/WHEEL
evolved_todo-1.5.0.dist-info/entry_points.txt
evolved_todo-1.5.0.dist-info/licenses/LICENSE
evolved_todo-1.5.0.dist-info/RECORD
