Metadata-Version: 2.4
Name: evolved-todo
Version: 1.5.0
Summary: Enhanced CLI-based todo application with rich visual formatting
Project-URL: Homepage, https://github.com/aliaskari/evolved-todo
Project-URL: Repository, https://github.com/aliaskari/evolved-todo
Project-URL: Issues, https://github.com/aliaskari/evolved-todo/issues
Author-email: Ali Askari <ali@example.com>
License: MIT
License-File: LICENSE
Keywords: cli,productivity,rich,task-manager,todo
Classifier: Development Status :: 4 - Beta
Classifier: Environment :: Console
Classifier: Intended Audience :: Developers
Classifier: Intended Audience :: End Users/Desktop
Classifier: License :: OSI Approved :: MIT License
Classifier: Operating System :: OS Independent
Classifier: Programming Language :: Python :: 3
Classifier: Programming Language :: Python :: 3.9
Classifier: Programming Language :: Python :: 3.10
Classifier: Programming Language :: Python :: 3.11
Classifier: Programming Language :: Python :: 3.12
Classifier: Programming Language :: Python :: 3.13
Classifier: Topic :: Office/Business :: Scheduling
Classifier: Topic :: Utilities
Requires-Python: >=3.9
Requires-Dist: rich<14.0.0,>=13.0.0
